CEApy/CEApy.py
CEApy/__init__.py
CEApy/tests.py
CEApy/cea-exec/FCEA2m.exe
CEApy/cea-exec/cea_python.bat
CEApy/cea-exec/cea_python.vbs
CEApy/cea-exec/cea_python_input.txt
CEApy/cea-exec/thermo.inp
CEApy/cea-exec/thermo.lib
CEApy/cea-exec/thermo.txt
CEApy/cea-exec/thermo_convertido.txt
CEApy/cea-exec/trans.inp
CEApy/cea-exec/trans.lib
CEApy-1.0.5.dist-info/LICENSE
CEApy-1.0.5.dist-info/METADATA
CEApy-1.0.5.dist-info/WHEEL
CEApy-1.0.5.dist-info/top_level.txt
CEApy-1.0.5.dist-info/RECORD
