Metadata-Version: 2.1
Name: CEApy
Version: 1.0.5
Summary: Library to automate analyzes in CEA NASA - Under development
Home-page: https://github.com/juliomachad0/CEApy.git
Author: Julio C. R. Machado
Author-email: julioromac@outlook.com
Classifier: Programming Language :: Python :: 3.11
Classifier: License :: OSI Approved :: MIT License
Classifier: Operating System :: OS Independent
Requires-Python: >=3.10
License-File: LICENSE
Requires-Dist: pandas (>=1.5.2)
